coge/__init__.py
coge/__main__.py
coge/coge.py
coge/binaryornot/__init__.py
coge/binaryornot/check.py
coge/binaryornot/helpers.py
coge/logx/__init__.py
coge/logx/colored_handler.py
coge/logx/logging.yaml
coge/logx/setup_logging.py
coge-0.1.9.dist-info/METADATA
coge-0.1.9.dist-info/WHEEL
coge-0.1.9.dist-info/entry_points.txt
coge-0.1.9.dist-info/top_level.txt
coge-0.1.9.dist-info/RECORD
