Metadata-Version: 2.1
Name: coge
Version: 0.1.9
Summary: this is a description
Home-page: https://github.com/zk4/coge
Download-URL: https://github.com/zk4/coge/archive/master.zip
Author: zk
Author-email: liuzq7@gmail.com
License: BSD
Keywords: best practice for python project
Classifier: Development Status :: 5 - Production/Stable
Classifier: Environment :: Console
Requires-Python: >3.0.0
Requires-Dist: binaryornot (==0.4.4)
Requires-Dist: chardet (==5.1.0)
Requires-Dist: PyYAML (==5.3.1)
